{
  "date": "2026-06-25",
  "theme": "connected",
  "tg_offset": 0,
  "plan": {
    "date": "2026-06-25",
    "theme": "connected",
    "slides": [
      "https://mauzhr1mqvtu52ju.public.blob.vercel-storage.com/ig-slides/d419654c767159d5aaaa82661fcc3c28.png",
      "https://mauzhr1mqvtu52ju.public.blob.vercel-storage.com/ig-slides/486217aee2cc9926a0737d3d0505c5a9.png",
      "https://mauzhr1mqvtu52ju.public.blob.vercel-storage.com/ig-slides/522a0b4f9fa71514eb0bcf4da8a9d1ef.png",
      "https://mauzhr1mqvtu52ju.public.blob.vercel-storage.com/ig-slides/8780c08b63e02562bb8e89fe5cb96be9.png",
      "https://mauzhr1mqvtu52ju.public.blob.vercel-storage.com/ig-slides/00ec33a4a037bb7a24891f0367def0c4.png",
      "https://mauzhr1mqvtu52ju.public.blob.vercel-storage.com/ig-slides/fc9d9ba66fe8341a0c6f2ba99fa58a66.png"
    ],
    "caption": "3 separate cards. One continuous illustration.\n\nLine them up and mashu's artwork becomes a single panorama, scattered across the set.\n\nWhich piece is your favorite? Tell us below.\n\npokeev.com prices every card live, so you always know what a set is really worth.\nlink in bio -> pokeev.com\n\n#pokemonart #connectingart #pokemonillustration #cardart #mashu #megaevolution #pokemon #pokemontcg #pokemoncards #pokemoncollector #tcg #pokemoncommunity #pokemoncardcollection #pokemoncollection #tcgcollector #pokemoncardgame #tradingcards #tradingcardgame #cardcollector #tcgcommunity #pokemoncardcollector #pokemontcgcollector #pokemonfan #pokemontcgcards #pokemontcgcommunity #pokemoncollectors #pokemonpulls #pokemonsealed #pullrate #pokemoninvesting",
    "hashtags": [
      "#pokemonart",
      "#connectingart",
      "#pokemonillustration",
      "#cardart",
      "#mashu",
      "#megaevolution",
      "#pokemon",
      "#pokemontcg",
      "#pokemoncards",
      "#pokemoncollector",
      "#tcg",
      "#pokemoncommunity",
      "#pokemoncardcollection",
      "#pokemoncollection",
      "#tcgcollector",
      "#pokemoncardgame",
      "#tradingcards",
      "#tradingcardgame",
      "#cardcollector",
      "#tcgcommunity",
      "#pokemoncardcollector",
      "#pokemontcgcollector",
      "#pokemonfan",
      "#pokemontcgcards",
      "#pokemontcgcommunity",
      "#pokemoncollectors",
      "#pokemonpulls",
      "#pokemonsealed",
      "#pullrate",
      "#pokemoninvesting"
    ],
    "brief": {
      "eyebrow": "BULBASAUR TO MEGA VENUSAUR EX",
      "headline": "They drew one scene.",
      "revealTitle": "Bulbasaur to Mega Venusaur ex",
      "caption": "3 separate cards. One continuous illustration.\n\nLine them up and mashu's artwork becomes a single panorama, scattered across the set.\n\nWhich piece is your favorite? Tell us below.\n\npokeev.com prices every card live, so you always know what a set is really worth.\nlink in bio -> pokeev.com",
      "hashtags": [
        "#pokemonart",
        "#connectingart",
        "#pokemonillustration",
        "#cardart",
        "#mashu",
        "#megaevolution",
        "#pokemon",
        "#pokemontcg",
        "#pokemoncards",
        "#pokemoncollector",
        "#tcg",
        "#pokemoncommunity",
        "#pokemoncardcollection",
        "#pokemoncollection",
        "#tcgcollector",
        "#pokemoncardgame",
        "#tradingcards",
        "#tradingcardgame",
        "#cardcollector",
        "#tcgcommunity",
        "#pokemoncardcollector",
        "#pokemontcgcollector",
        "#pokemonfan",
        "#pokemontcgcards",
        "#pokemontcgcommunity",
        "#pokemoncollectors",
        "#pokemonpulls",
        "#pokemonsealed",
        "#pullrate",
        "#pokemoninvesting"
      ]
    },
    "keys": [
      "mega-venusaur-line"
    ],
    "verify": [
      {
        "snap_usd": 25,
        "snap_eur": null,
        "live_usd": 25.11,
        "live_eur": null,
        "agree": true,
        "note": "agree",
        "display_usd": 25.11,
        "name": "Bulbasaur"
      },
      {
        "snap_usd": 25,
        "snap_eur": null,
        "live_usd": 23.44,
        "live_eur": null,
        "agree": true,
        "note": "agree",
        "display_usd": 23.44,
        "name": "Ivysaur"
      },
      {
        "snap_usd": 189,
        "snap_eur": null,
        "live_usd": 186.42,
        "live_eur": null,
        "agree": true,
        "note": "agree",
        "display_usd": 186.42,
        "name": "Mega Venusaur ex"
      }
    ],
    "qa_warnings": []
  },
  "ctx": {
    "theme": "connected",
    "base": "https://pokeev.com",
    "facts": {
      "key": "mega-venusaur-line",
      "group_id": "mega-venusaur-line",
      "theme_line": "Bulbasaur to Mega Venusaur ex",
      "artist": "mashu",
      "era": "Mega Evolution",
      "setLabel": "Mega Evolution",
      "setLogo": "https://images.pokemontcg.io/me1/logo.png",
      "items": [
        {
          "name": "Bulbasaur",
          "image": "https://images.pokemontcg.io/me1/133_hires.png",
          "usd": 25,
          "setLabel": "Mega Evolution",
          "setLogo": "https://images.pokemontcg.io/me1/logo.png",
          "ptcgId": "me1-133",
          "number": "133",
          "hd_image": "https://mauzhr1mqvtu52ju.public.blob.vercel-storage.com/ig-cards/a0a7e675735864d08dc91fa89cf20d95.png"
        },
        {
          "name": "Ivysaur",
          "image": "https://images.pokemontcg.io/me1/134_hires.png",
          "usd": 23,
          "setLabel": "Mega Evolution",
          "setLogo": "https://images.pokemontcg.io/me1/logo.png",
          "ptcgId": "me1-134",
          "number": "134",
          "hd_image": "https://mauzhr1mqvtu52ju.public.blob.vercel-storage.com/ig-cards/a11d73cd5a281866e4d214cefdfe872a.png"
        },
        {
          "name": "Mega Venusaur ex",
          "image": "https://images.pokemontcg.io/me1/177_hires.png",
          "usd": 186,
          "setLabel": "Mega Evolution",
          "setLogo": "https://images.pokemontcg.io/me1/logo.png",
          "ptcgId": "me1-177",
          "number": "177",
          "hd_image": "https://mauzhr1mqvtu52ju.public.blob.vercel-storage.com/ig-cards/e86a449b1ce75cbc621f334484f08bbe.png"
        }
      ],
      "total": 234
    },
    "verify": [
      {
        "snap_usd": 25,
        "snap_eur": null,
        "live_usd": 25.11,
        "live_eur": null,
        "agree": true,
        "note": "agree",
        "display_usd": 25.11,
        "name": "Bulbasaur"
      },
      {
        "snap_usd": 25,
        "snap_eur": null,
        "live_usd": 23.44,
        "live_eur": null,
        "agree": true,
        "note": "agree",
        "display_usd": 23.44,
        "name": "Ivysaur"
      },
      {
        "snap_usd": 189,
        "snap_eur": null,
        "live_usd": 186.42,
        "live_eur": null,
        "agree": true,
        "note": "agree",
        "display_usd": 186.42,
        "name": "Mega Venusaur ex"
      }
    ],
    "keys": [
      "mega-venusaur-line"
    ]
  }
}