{
  "date": "2026-07-01",
  "theme": "grails",
  "tg_offset": 0,
  "plan": {
    "date": "2026-07-01",
    "theme": "grails",
    "slides": [
      "https://mauzhr1mqvtu52ju.public.blob.vercel-storage.com/ig-slides/988f57dd995d963dfad4f1c0056cff24.png",
      "https://mauzhr1mqvtu52ju.public.blob.vercel-storage.com/ig-slides/c490ad77a7fba28b36b5ca7db5792fc3.png",
      "https://mauzhr1mqvtu52ju.public.blob.vercel-storage.com/ig-slides/0dec244f886e4810a0e913caa6687693.png",
      "https://mauzhr1mqvtu52ju.public.blob.vercel-storage.com/ig-slides/a5730e492a36dd7577855e67681fddd5.png",
      "https://mauzhr1mqvtu52ju.public.blob.vercel-storage.com/ig-slides/2a1b727b06957d1e8cf0d048837d81c1.png",
      "https://mauzhr1mqvtu52ju.public.blob.vercel-storage.com/ig-slides/99a5385210420dab4f40bb3c3cd72f35.png"
    ],
    "caption": "A single Mudkip Star from EX Team Rocket Returns is sitting at $2,793 on the market right now.\n\nGold star. 214 to 1 pull odds from a sealed booster. Masakazu Fukuda's art shows Mudkip gliding through a starfield, and the market has decided that image is worth nearly three thousand dollars.\n\nTo pull one copy at those odds you are cracking enough packs to make the sealed math genuinely painful. The card itself outpaces nearly every box EV calculation on pokeev.com by a significant margin.\n\nSave this before you decide whether to open any vintage EX-era product.\n\nRip or hold at $2,793, where do you land?\n\nFollow @pokeev.tcg for the live Expected Value on every sealed set.\nLink in bio. pokeev.com\n\n#pokemongrails #grailcard #pokemonart #pokemoninvesting #mudkipstar #exteamrocketreturns #goldstar #masakazufukuda #sealedpokemon #pokemoncollector",
    "hashtags": [
      "#pokemongrails",
      "#grailcard",
      "#pokemonart",
      "#pokemoninvesting",
      "#mudkipstar",
      "#exteamrocketreturns",
      "#goldstar",
      "#masakazufukuda",
      "#sealedpokemon",
      "#pokemoncollector"
    ],
    "brief": {
      "shockHeadline": "Worth more than|most people guess",
      "priceNote": "for a single card",
      "compare": null,
      "cardKicker": "THE CARD",
      "cardHeadline": "Mudkip Star",
      "cardBody": "EX Team Rocket Returns's crown jewel.|The card the whole set chases.",
      "craftKicker": "THE ARTIST",
      "craftHeadline": "Masakazu Fukuda",
      "craftBody": "A single round eye catches the light | Subtle gradient shading across the blue skin",
      "craftZoom": {
        "zw": 2700,
        "zx": -540,
        "zy": -381
      },
      "sceneKicker": "THE SCENE",
      "sceneHeadline": "Mudkip Star gliding through a starfield",
      "sceneBody": "Mudkip hovers weightless in a deep glittering cosmos | Soft blue body and orange gills glow under the holographic sheen",
      "sceneZoom": {
        "zw": 2700,
        "zx": -1620,
        "zy": -381
      },
      "oddsBody": "Rip a sealed booster.|The odds are 214 to 1.",
      "caption": "A single Mudkip Star from EX Team Rocket Returns is sitting at $2,793 on the market right now.\n\nGold star. 214 to 1 pull odds from a sealed booster. Masakazu Fukuda's art shows Mudkip gliding through a starfield, and the market has decided that image is worth nearly three thousand dollars.\n\nTo pull one copy at those odds you are cracking enough packs to make the sealed math genuinely painful. The card itself outpaces nearly every box EV calculation on pokeev.com by a significant margin.\n\nSave this before you decide whether to open any vintage EX-era product.\n\nRip or hold at $2,793, where do you land?\n\nFollow @pokeev.tcg for the live Expected Value on every sealed set.\nLink in bio. pokeev.com",
      "hashtags": [
        "#pokemongrails",
        "#grailcard",
        "#pokemonart",
        "#pokemoninvesting",
        "#mudkipstar",
        "#exteamrocketreturns",
        "#goldstar",
        "#masakazufukuda",
        "#sealedpokemon",
        "#pokemoncollector"
      ]
    },
    "keys": [
      "ex7-107"
    ],
    "verify": [
      {
        "snap_usd": 4000,
        "snap_eur": null,
        "live_usd": 2793,
        "live_eur": 3101.79,
        "agree": false,
        "note": "no TCGplayer market — PriceCharting sold $2,793 (lone ask $4,000, 30% off)",
        "display_usd": 2793,
        "pc_usd": 2793,
        "name": "Mudkip Star"
      }
    ],
    "qa_warnings": []
  },
  "ctx": {
    "theme": "grails",
    "base": "https://pokeev.com",
    "facts": {
      "_usd": 3999.99,
      "key": "ex7-107",
      "card_id": "ex7-107",
      "set_id": "ex-team-rocket-returns",
      "set_name": "EX Team Rocket Returns",
      "logo": "https://assets.tcgdex.net/en/ex/ex7/logo.webp",
      "name": "Mudkip Star",
      "rarity": "gold-star",
      "image": "https://images.pokemontcg.io/ex7/107_hires.png",
      "usd": 2793,
      "odds_n": 214,
      "booster": "https://tcgplayer-cdn.tcgplayer.com/product/98578_in_1000x1000.jpg",
      "artist": "Masakazu Fukuda",
      "hd_image": "https://mauzhr1mqvtu52ju.public.blob.vercel-storage.com/ig-cards/7b3b1d38ce906910ed675395ee61f1d5.png",
      "booster_hd": "https://mauzhr1mqvtu52ju.public.blob.vercel-storage.com/ig-cards/65c16b3da19287af979e6f61acae8a04.png",
      "vision": {
        "subject": "Mudkip Star floating against a sparkling cosmic background",
        "hidden": "",
        "sceneCenterX": 0.5,
        "sceneCenterY": 0.34,
        "sceneFactor": 1.9,
        "sceneHeadline": "Mudkip Star gliding through a starfield",
        "sceneBody": "The rare Gold Star Mudkip hovers weightless against a deep glittering cosmos | Its soft blue body and vivid orange gills glow under the holographic sheen",
        "craftCenterX": 0.44,
        "craftCenterY": 0.29,
        "craftFactor": 3.4,
        "craftHeadline": "Mudkip's wide reflective eye up close",
        "craftBody": "A single round eye catches the light with a crisp white highlight at its center | The surrounding blue skin shows subtle gradient shading in Masakazu Fukuda's illustration",
        "compare": "a premium noise-canceling headphone set",
        "compareUsd": 380,
        "craftZoom": {
          "zw": 4012,
          "zx": -1225,
          "zy": -1142
        },
        "sceneZoom": {
          "zw": 2242,
          "zx": -581,
          "zy": -582
        }
      },
      "crops": {
        "craft": {
          "zw": 2700,
          "zx": -540,
          "zy": -381
        },
        "scene": {
          "zw": 2700,
          "zx": -1620,
          "zy": -381
        }
      }
    },
    "verify": [
      {
        "snap_usd": 4000,
        "snap_eur": null,
        "live_usd": 2793,
        "live_eur": 3101.79,
        "agree": false,
        "note": "no TCGplayer market — PriceCharting sold $2,793 (lone ask $4,000, 30% off)",
        "display_usd": 2793,
        "pc_usd": 2793,
        "name": "Mudkip Star"
      }
    ],
    "keys": [
      "ex7-107"
    ]
  },
  "handled_seq": 0,
  "handled_format_seq": 0
}